eaglevision/__init__.py
eaglevision/__main__.py
eaglevision/base_eagle.py
eaglevision/cloc_eagle.py
eaglevision/cyclomatic_eagle.py
eaglevision/eaglevision.py
eaglevision/report_style.css
eaglevision/similarity_eagle.py
EagleVision-0.0.6.dist-info/LICENSE.md
EagleVision-0.0.6.dist-info/METADATA
EagleVision-0.0.6.dist-info/WHEEL
EagleVision-0.0.6.dist-info/top_level.txt
EagleVision-0.0.6.dist-info/RECORD
