Metadata-Version: 2.1
Name: EagleVision
Version: 0.0.6
Summary: EagleVision
Home-page: https://github.com/philips-internal/EagleVision
Author: Brijesh
Author-email: brijesh.krishnank@philips.com
License: UNKNOWN
Platform: UNKNOWN
Classifier: Programming Language :: Python :: 3
Classifier: License :: OSI Approved :: MIT License
Classifier: Operating System :: OS Independent
Requires-Python: >=3.7
Requires-Dist: functiondefextractor (==0.1.2)
Requires-Dist: similarity-processor (==0.1.1)
Requires-Dist: lizard (==1.17.3)
